microday/__init__.py
microday/__main__.py
microday/__version__.py
microday/microday.py
microday-1.0.0.dist-info/METADATA
microday-1.0.0.dist-info/RECORD
microday-1.0.0.dist-info/WHEEL
microday-1.0.0.dist-info/top_level.txt
